{
  "produtos": [
    {
      "id": "1",
      "categoria": "Alimentação",
      "nome": "Arroz",
      "vlr": "10",
      "qtd": "2"
    },
    {
      "id": "2",
      "categoria": "Habitação",
      "nome": "Conta Água",
      "vlr": "50",
      "qtd": "1"
    },
    {
      "id": "3",
      "categoria": "Lazer",
      "nome": "Cinema",
      "vlr": "25",
      "qtd": "2"
    },
    {
      "id": "4",
      "categoria": "Saúde",
      "nome": "Remédio",
      "vlr": "150",
      "qtd": "1"
    }
  ],
  "dates": [
    {
      "data": "2023-08-01",
      "id": 1
    }
  ],
  "orcamentos": [
    {
      "orcamento": "200",
      "id": 1
    }
  ]
}